{
  "name": "Brawl Chess",
  "description": "Are you ready to become a champion? Choose your hero and challenge other players in this family-friendly game with a lively cartoon style. Train your brain and bond with your loved ones at the same time. \n\nIn this fantasy world, one of brave heroes leads your chess army to victory. \n\nCartoon visuals make the game accessible to everyone. What’s going on there! Arrows fly above heads and swords break in the heat of battle. Or maybe you prefer classic chess? You can always change your pieces to traditional ones.\n\nBrawl Chess connects generations in a multiplayer, but a single player will also appeal to players of all ages. There are 5 levels of difficulty. The first is great for children to learn. The fifth is suited for chess veterans who are looking for a serious challenge.\n\nKey features:\n\nLOCAL MULTIPLAYER. Your family will absolutely love this version of chess. Do you fancy a happy competition between parents and children? It is possible. Invite grandparents too, they certainly know the rules.\n\nKIDS-FRIENDLY. It's a game for the whole family, easy to learn and cheerful. Play it regardless of age. Thanks to the vibrant cartoon style, children will also join the fun.\n\nBRAIN TRAINING. But in a fun way! Brawl Chess looks modern while still being one of the oldest and most popular games in the world with all its advantages. It increases IQ, improves arithmetic skills, teaches analytical and critical thinking. Train to use both hemispheres of your brain.\n\nCREATIVITY BOOST. The fun doesn't have to end after turning off the console. When the father plays as a ghost, and the son plays as a prince, they can perform scenes with these characters after the chess game ends.",
  "titleId": "010068F00F444000",
  "img": "https://img-eshop.cdn.nintendo.net/i/fc3b07740621039d46e01ae151405abcfc1683a8a5e76867b88d3381c43c79e6.jpg",
  "tests": [
    {
      "tester": null,
      "rating": 5,
      "details": null,
      "test_date": "2021-02-27T22:39:01.098",
      "cpu": "AMD Ryzen 9 3900X 12-Core Processor            ",
      "gpu": "GeForce RTX 2080 SUPER/PCIe/SSE2",
      "version": "320f6f9",
      "os": "Windows",
      "from_yuzu": true
    }
  ]
}