{
  "name": "Revenant Saga",
  "description": "After being turned into an immortal being known as a \"Revenant\" and learning of the existence of a demon within him, Albert sets out on a journey to make the person who did this to him pay with their very life. However, as he runs into others along the way dealing with their own figurative demons, what is the answer he finds...?\n\nBoasting a story that blurs the lines between good and evil, and plenty of content to go around, this is one title not to be missed! This includes a variety of unique subquests, in-battle transformation systems, as well as a weapon forging system allowing players to make entirely unique weapons as they battle in turn-based battles with 3D animation!",
  "titleId": "0100AA2006510000",
  "img": "https://img-eshop.cdn.nintendo.net/i/2345fdffa503ece02bfa11fdee2c796451a7feea56151203ea1df3ce34acb587.jpg",
  "tests": [
    {
      "tester": null,
      "rating": 3,
      "details": null,
      "test_date": "2019-03-05T02:47:01.043",
      "cpu": "AMD A8-7600 Radeon R7, 10 Compute Cores 4C+6G  ",
      "gpu": "AMD Radeon HD 7700 Series",
      "version": "c5abe59",
      "os": "Windows",
      "from_yuzu": true
    }
  ]
}