{
  "name": "Super Chariot",
  "description": "Designed for the Nintendo Switch™, Super Chariot is a 2D platform game that can be played through to the end in either solo or co-op mode. You play as either the brave Princess or her faithful fiancé in a subterranean fantasy adventure... \n\nManoeuvre the wheeled coffin of the dead King through 25 levels and 5 colourful environments, trying to ignore the incessant insults of the King's ghost.\n\nWith original gameplay and an innovative physics engine, hours of exciting exploration, hair-raising sliding sequences and mountains of treasure lie ahead!\n\nSet out on an epic adventure and give His Majesty the trip of his death. Guide a Super Chariot containing the remains of your King through a network of subterranean caverns.  On your own or with a friend, lead the brave Princess and her faithful fiancé through the catacombs in search of the ideal resting spot for the King!\n\nThe Super Chariot's large wheels enable the heroes to cross crevasses, climb and perform all sorts of perilous manoeuvres. Take the riches from the walls of the many varied environments, find the exit and avoid (or repulse) all the different enemies who try to steal your hard-earned loot! Put your skill, coordination and daring to the test as you try to finish all the levels and dangers aplenty in Super Chariot. Effective teamwork will open up even more possibilities...\n\n• Play with a friend in local multiplayer on your Nintendo Switch™ in TV or Tabletop mode\n• Epic challenges await the two of you: cooperation is key\n• Wonderful 2D worlds, peppered with unique characters and items \n• Over 60 hours of gameplay await, as you make your way through 25 levels dotted with secret pathways and bountiful treasure",
  "titleId": "010065F004E5E000",
  "img": "https://img-eshop.cdn.nintendo.net/i/b958d73ed12a3958e18c814c6f7fe79f5771e6f7c766bd801b6abbf341534c14.jpg",
  "tests": [
    {
      "tester": "capiqua",
      "rating": 4,
      "details": null,
      "test_date": "2021-01-30T11:01:44.452",
      "cpu": "Intel(R) Core(TM) i3-10100 CPU @ 3.60GHz",
      "gpu": "GeForce GTX 1650 SUPER/PCIe/SSE2",
      "version": "52b1362",
      "os": "Windows",
      "from_yuzu": true
    },
    {
      "tester": null,
      "rating": 2,
      "details": null,
      "test_date": "2019-06-19T17:55:58.544",
      "cpu": "Intel(R) Core(TM) i7-4790K CPU @ 4.00GHz",
      "gpu": "GeForce GTX 970/PCIe/SSE2",
      "version": "37c7782",
      "os": "Windows",
      "from_yuzu": true
    },
    {
      "tester": null,
      "rating": 3,
      "details": null,
      "test_date": "2021-09-13T15:34:12.82",
      "cpu": "AMD Ryzen 5 3600 6-Core Processor              ",
      "gpu": "NVIDIA GeForce GTX 1050 Ti/PCIe/SSE2",
      "version": "462d7bd",
      "os": "Windows",
      "from_yuzu": true
    }
  ]
}