{
  "name": "Xenon Valkyrie+",
  "description": "Xenon Valkyrie+ is a rogue-like platformer game in which you must fight to the deepest part of a moon and halt the plans of a wicked witch.\n\nObtain many weapons as you fight through a unique, randomly-generated world every time you play. Encounter many characters, stores and enemies that tell a legendary story.\n\nWith traditional graphics and high quality chiptune music, level up and get the amazing power of the Xenon Valkyrie!\n\n- Rogue-lite platformer with a great story\n- Many worlds with different routes\n- 3 heroes with unique skills\n- 100+ items\n- Multiple bosses and enemies \n- RPG elements\n- Several endings and secrets\n- Quality Chiptune music\n- Hard gameplay and Permadeath",
  "titleId": "010064200C324000",
  "img": "https://img-eshop.cdn.nintendo.net/i/8f25fb3f271d0d0fffcf3daa94bfacf0a3c7f87a622f1cf622fd6542b3da78aa.jpg",
  "tests": [
    {
      "tester": null,
      "rating": 1,
      "details": null,
      "test_date": "2019-03-05T16:35:53.691",
      "cpu": "AMD A8-7600 Radeon R7, 10 Compute Cores 4C+6G  ",
      "gpu": "AMD Radeon HD 7700 Series",
      "version": "c5abe59",
      "os": "Windows",
      "from_yuzu": true
    },
    {
      "tester": null,
      "rating": 2,
      "details": null,
      "test_date": "2021-05-21T23:31:24.424",
      "cpu": "AMD Ryzen 7 1700 Eight-Core Processor          ",
      "gpu": "NVIDIA GeForce GTX 1070",
      "version": "004c7bf",
      "os": "Windows",
      "from_yuzu": true
    },
    {
      "tester": null,
      "rating": 3,
      "details": null,
      "test_date": "2021-03-21T05:19:25.997",
      "cpu": "AMD Ryzen 7 1700 Eight-Core Processor          ",
      "gpu": "GeForce GTX 1070",
      "version": "fc9cd29",
      "os": "Windows",
      "from_yuzu": true
    },
    {
      "tester": null,
      "rating": 1,
      "details": null,
      "test_date": "2019-04-05T14:14:31.406",
      "cpu": "Intel(R) Core(TM) i3-6100U CPU @ 2.30GHz",
      "gpu": "Intel(R) HD Graphics 520",
      "version": "bb8903e",
      "os": "Windows",
      "from_yuzu": true
    },
    {
      "tester": null,
      "rating": 3,
      "details": null,
      "test_date": "2021-05-15T05:35:06.614",
      "cpu": "AMD Ryzen 7 1700 Eight-Core Processor          ",
      "gpu": "NVIDIA GeForce GTX 1070",
      "version": "8061b27",
      "os": "Windows",
      "from_yuzu": true
    },
    {
      "tester": null,
      "rating": 2,
      "details": null,
      "test_date": "2021-04-28T03:33:01.678",
      "cpu": "AMD Ryzen 7 1700 Eight-Core Processor          ",
      "gpu": "NVIDIA GeForce GTX 1070",
      "version": "cebacd9",
      "os": "Windows",
      "from_yuzu": true
    },
    {
      "tester": null,
      "rating": 2,
      "details": null,
      "test_date": "2021-04-11T07:48:57.913",
      "cpu": "AMD Ryzen 7 1700 Eight-Core Processor          ",
      "gpu": "NVIDIA GeForce GTX 1070",
      "version": "108df67",
      "os": "Windows",
      "from_yuzu": true
    },
    {
      "tester": null,
      "rating": 3,
      "details": null,
      "test_date": "2021-05-08T01:46:21.164",
      "cpu": "AMD Ryzen 7 1700 Eight-Core Processor          ",
      "gpu": "NVIDIA GeForce GTX 1070",
      "version": "f6bf40b",
      "os": "Windows",
      "from_yuzu": true
    },
    {
      "tester": null,
      "rating": 3,
      "details": null,
      "test_date": "2021-03-25T02:21:23.18",
      "cpu": "AMD Ryzen 7 1700 Eight-Core Processor          ",
      "gpu": "GeForce GTX 1070",
      "version": "41b7dcf",
      "os": "Windows",
      "from_yuzu": true
    },
    {
      "tester": null,
      "rating": 2,
      "details": null,
      "test_date": "2021-03-20T00:33:07.938",
      "cpu": "AMD Ryzen 7 1700 Eight-Core Processor          ",
      "gpu": "GeForce GTX 1070",
      "version": "e7c0648",
      "os": "Windows",
      "from_yuzu": true
    }
  ]
}